[
    {
        "idx": "m1",
        "url": "./assets/img/avatar-m1.jpg"
    },
    {
        "idx": "m2",
        "url": "./assets/img/avatar-m2.jpg"
    },
    {
        "idx": "m3",
        "url": "./assets/img/avatar-m3.jpg"
    },
    {
        "idx": "m4",
        "url": "./assets/img/avatar-m4.jpg"
    },
    {
        "idx": "m5",
        "url": "./assets/img/avatar-m5.jpg"
    },
    {
        "idx": "m6",
        "url": "./assets/img/avatar-m6.jpg"
    },
    {
        "idx": "m7",
        "url": "./assets/img/avatar-m7.jpg"
    },
    {
        "idx": "m8",
        "url": "./assets/img/avatar-m8.jpg"
    },
    {
        "idx": "m9",
        "url": "./assets/img/avatar-m9.jpg"
    },
    {
        "idx": "m10",
        "url": "./assets/img/avatar-m10.jpg"
    },
    {
        "idx": "m11",
        "url": "./assets/img/avatar-m11.jpg"
    },    {
        "idx": "w1",
        "url": "./assets/img/avatar-w1.jpg"
    },
    {
        "idx": "w2",
        "url": "./assets/img/avatar-w2.jpg"
    },
    {
        "idx": "w3",
        "url": "./assets/img/avatar-w3.jpg"
    },
    {
        "idx": "w4",
        "url": "./assets/img/avatar-w4.jpg"
    },
    {
        "idx": "w5",
        "url": "./assets/img/avatar-w5.jpg"
    },
    {
        "idx": "w6",
        "url": "./assets/img/avatar-w6.jpg"
    },
    {
        "idx": "w7",
        "url": "./assets/img/avatar-w7.jpg"
    },
    {
        "idx": "w8",
        "url": "./assets/img/avatar-w8.jpg"
    },
    {
        "idx": "w9",
        "url": "./assets/img/avatar-w9.jpg"
    },
    {
        "idx": "w10",
        "url": "./assets/img/avatar-10.jpg"
    }
]